traversalkit.py
TraversalKit-0.2.dist-info/top_level.txt
TraversalKit-0.2.dist-info/RECORD
TraversalKit-0.2.dist-info/zip-safe
TraversalKit-0.2.dist-info/METADATA
TraversalKit-0.2.dist-info/metadata.json
TraversalKit-0.2.dist-info/DESCRIPTION.rst
TraversalKit-0.2.dist-info/WHEEL
