Metadata-Version: 2.0
Name: TraversalKit
Version: 0.2
Summary: Helper library for Pyramid applications based on Traversal
Home-page: https://bitbucket.org/kr41/traversalkit
Author: Dmitry Vakhrushev
Author-email: self@kr41.net
License: BSD
Download-URL: https://bitbucket.org/kr41/traversalkit/downloads
Keywords: pyramid traversal resources
Platform: UNKNOWN
Classifier: License :: OSI Approved :: BSD License
Classifier: Programming Language :: Python
Classifier: Programming Language :: Python :: 2.6
Classifier: Programming Language :: Python :: 2.7
Classifier: Programming Language :: Python :: 3.3
Classifier: Programming Language :: Python :: 3.4
Classifier: Programming Language :: Python :: Implementation :: PyPy
Classifier: Programming Language :: Python :: Implementation :: CPython
Classifier: Topic :: Software Development :: Libraries :: Python Modules
Classifier: Intended Audience :: Developers
Classifier: Framework :: Pyramid
